google_vm_scheduler/__init__.py
google_vm_scheduler/scheduler.py
google_vm_scheduler-0.1.1.dist-info/LICENCE
google_vm_scheduler-0.1.1.dist-info/METADATA
google_vm_scheduler-0.1.1.dist-info/WHEEL
google_vm_scheduler-0.1.1.dist-info/top_level.txt
google_vm_scheduler-0.1.1.dist-info/RECORD
