Metadata-Version: 2.1
Name: google-vm-scheduler
Version: 0.1.1
Summary: A package for scheduling virtual machines on Google Cloud
Home-page: https://github.com/jbloxsome/google-vm-scheduler
Author: Joe Bloxsome
Author-email: joe@bloxso.me
License: UNKNOWN
Project-URL: Bug Tracker, https://github.com/jbloxsome/google-vm-scheduler/issues
Platform: UNKNOWN
Classifier: Programming Language :: Python :: 3
Classifier: License :: OSI Approved :: MIT License
Classifier: Operating System :: OS Independent
Requires-Python: >=3.9
License-File: LICENCE
Requires-Dist: google-cloud-compute
